next/__init__.py
next/asset.py
next/category.py
next/channel.py
next/client.py
next/embed.py
next/emoji.py
next/enums.py
next/errors.py
next/file.py
next/flags.py
next/http.py
next/invite.py
next/member.py
next/message.py
next/messageable.py
next/permissions.py
next/permissions_calculator.py
next/py.typed
next/role.py
next/server.py
next/state.py
next/user.py
next/utils.py
next/websocket.py
next/ext/__init__.py
next/ext/commands/__init__.py
next/ext/commands/checks.py
next/ext/commands/client.py
next/ext/commands/cog.py
next/ext/commands/command.py
next/ext/commands/context.py
next/ext/commands/converters.py
next/ext/commands/cooldown.py
next/ext/commands/errors.py
next/ext/commands/group.py
next/ext/commands/help.py
next/ext/commands/utils.py
next/ext/commands/view.py
next/types/__init__.py
next/types/category.py
next/types/channel.py
next/types/embed.py
next/types/emoji.py
next/types/file.py
next/types/gateway.py
next/types/http.py
next/types/invite.py
next/types/member.py
next/types/message.py
next/types/permissions.py
next/types/role.py
next/types/server.py
next/types/user.py
next_api_py-0.2.0.dist-info/METADATA
next_api_py-0.2.0.dist-info/WHEEL
next_api_py-0.2.0.dist-info/licenses/LICENSE
next_api_py-0.2.0.dist-info/RECORD
